{
  "project_info": {
    "project_number": "978502887490",
    "project_id": "newp-b7112",
    "storage_bucket": "newp-b7112.firebasestorage.app"
  },
  "client": [
    {
      "client_info": {
        "mobilesdk_app_id": "1:978502887490:android:50779552d781eada2da5db",
        "android_client_info": {
          "package_name": "com.africa.men.fashion.design.styles"
        }
      },
      "oauth_client": [],
      "api_key": [
        {
          "current_key": "AIzaSyB4rYmzFwG-gH84NwtbH3Kj6m3ZUL5ogmk"
        }
      ],
      "services": {
        "appinvite_service": {
          "other_platform_oauth_client": []
        }
      }
    },
    {
      "client_info": {
        "mobilesdk_app_id": "1:978502887490:android:238e16e34b6f5cb32da5db",
        "android_client_info": {
          "package_name": "com.africa.women.fashion.design.styles"
        }
      },
      "oauth_client": [],
      "api_key": [
        {
          "current_key": "AIzaSyB4rYmzFwG-gH84NwtbH3Kj6m3ZUL5ogmk"
        }
      ],
      "services": {
        "appinvite_service": {
          "other_platform_oauth_client": []
        }
      }
    },
    {
      "client_info": {
        "mobilesdk_app_id": "1:978502887490:android:29c26178745dc9072da5db",
        "android_client_info": {
          "package_name": "com.boys.men.hairstles.haircut.styles.fashion"
        }
      },
      "oauth_client": [],
      "api_key": [
        {
          "current_key": "AIzaSyB4rYmzFwG-gH84NwtbH3Kj6m3ZUL5ogmk"
        }
      ],
      "services": {
        "appinvite_service": {
          "other_platform_oauth_client": []
        }
      }
    }
  ],
  "configuration_version": "1"
}